zig_minesolver/__init__.py
zig_minesolver/zig-main
zig_minesolver-0.1.1.dist-info/METADATA
zig_minesolver-0.1.1.dist-info/WHEEL
zig_minesolver-0.1.1.dist-info/top_level.txt
zig_minesolver-0.1.1.dist-info/RECORD
