Metadata-Version: 2.1
Name: zig-minesolver
Version: 0.1.1
Summary: Minesweeper solver in Zig
Home-page: https://github.com/LewisGaul/minesolver
Author: Lewis Gaul
Maintainer: Lewis Gaul
License: UNKNOWN
Platform: UNKNOWN
Classifier: Programming Language :: Python :: 3
Classifier: Programming Language :: Python :: 3.6
Classifier: Programming Language :: Python :: 3.7
Classifier: Programming Language :: Python :: 3.8
Classifier: Programming Language :: Python :: 3.9
Classifier: Development Status :: 3 - Alpha
